plexe/__init__.py
plexe/agents/__init__.py
plexe/agents/agents.py
plexe/agents/conversational.py
plexe/agents/dataset_analyser.py
plexe/agents/dataset_splitter.py
plexe/agents/feature_engineer.py
plexe/agents/model_packager.py
plexe/agents/model_planner.py
plexe/agents/model_tester.py
plexe/agents/model_trainer.py
plexe/agents/schema_resolver.py
plexe/callbacks.py
plexe/config.py
plexe/core/__init__.py
plexe/core/entities/__init__.py
plexe/core/entities/solution.py
plexe/core/interfaces/__init__.py
plexe/core/interfaces/feature_transformer.py
plexe/core/interfaces/predictor.py
plexe/core/object_registry.py
plexe/core/state.py
plexe/core/storage.py
plexe/datasets.py
plexe/fileio.py
plexe/internal/__init__.py
plexe/internal/common/__init__.py
plexe/internal/common/datasets/__init__.py
plexe/internal/common/datasets/adapter.py
plexe/internal/common/datasets/interface.py
plexe/internal/common/datasets/tabular.py
plexe/internal/common/provider.py
plexe/internal/common/utils/__init__.py
plexe/internal/common/utils/agents.py
plexe/internal/common/utils/chain_of_thought/__init__.py
plexe/internal/common/utils/chain_of_thought/adapters.py
plexe/internal/common/utils/chain_of_thought/callable.py
plexe/internal/common/utils/chain_of_thought/emitters.py
plexe/internal/common/utils/chain_of_thought/protocol.py
plexe/internal/common/utils/dataset_storage.py
plexe/internal/common/utils/dependency_utils.py
plexe/internal/common/utils/markdown_utils.py
plexe/internal/common/utils/model_state.py
plexe/internal/common/utils/model_utils.py
plexe/internal/common/utils/pandas_utils.py
plexe/internal/common/utils/prompt_utils.py
plexe/internal/common/utils/pydantic_utils.py
plexe/internal/common/utils/response.py
plexe/internal/datasets/__init__.py
plexe/internal/datasets/config.py
plexe/internal/datasets/core/__init__.py
plexe/internal/datasets/core/generation/__init__.py
plexe/internal/datasets/core/generation/base.py
plexe/internal/datasets/core/generation/simple_llm.py
plexe-0.26.2.dist-info/LICENSE
plexe-0.26.2.dist-info/METADATA
plexe-0.26.2.dist-info/WHEEL
plexe-0.26.2.dist-info/entry_points.txt
plexe-0.26.2.dist-info/RECORD
