Metadata-Version: 2.3
Name: plexe
Version: 0.26.2
Summary: An agentic framework for building ML models from natural language
License: Apache-2.0
Keywords: agent,custom ai,llm,machine learning,data generation
Author: Marcello De Bernardi
Author-email: mdebernardi@plexe.ai
Requires-Python: >=3.11,<3.13
Classifier: Development Status :: 3 - Alpha
Classifier: Intended Audience :: Developers
Classifier: Intended Audience :: Science/Research
Classifier: License :: OSI Approved :: Apache Software License
Classifier: Programming Language :: Python :: 3
Classifier: Programming Language :: Python :: 3.11
Classifier: Programming Language :: Python :: 3.12
Classifier: Topic :: Scientific/Engineering :: Artificial Intelligence
Classifier: Topic :: Software Development :: Libraries :: Python Modules
Provides-Extra: all
Provides-Extra: chatui
Provides-Extra: transformers
Requires-Dist: accelerate (==0.24.1) ; extra == "transformers" or extra == "all"
Requires-Dist: bandit (>=1.8.2,<2.0.0)
Requires-Dist: black (>=24.10.0,<25.0.0)
Requires-Dist: dataclasses-json (>=0.6.7,<0.7.0)
Requires-Dist: deprecated (>=1.2.18,<2.0.0)
Requires-Dist: fastapi (>=0.115.12,<0.116.0) ; extra == "chatui" or extra == "all"
Requires-Dist: hypothesis (>=6.125.1,<7.0.0)
Requires-Dist: imbalanced-learn (>=0.12.4,<0.13.0)
Requires-Dist: jinja2 (>=3.1.6,<4.0.0)
Requires-Dist: joblib (>=1.4.2,<2.0.0)
Requires-Dist: litellm (==1.65.8)
Requires-Dist: mlflow (>=3.0.0rc2,<4.0.0)
Requires-Dist: mlxtend (>=0.23.4,<0.24.0)
Requires-Dist: numpy (>=1.23.2,<2.0.0)
Requires-Dist: pandas (>=1.5.0,<=2.2.0)
Requires-Dist: platformdirs (>=4.3.7,<5.0.0)
Requires-Dist: pyarrow (>=19.0.0,<20.0.0)
Requires-Dist: pydantic (>=2.9.2,<3.0.0)
Requires-Dist: ray (>=2.9.0,<3.0.0)
Requires-Dist: rich (>=13.7.1,<14.0.0)
Requires-Dist: safetensors (>=0.4.1,<0.5.0) ; extra == "transformers" or extra == "all"
Requires-Dist: scikit-learn (>=1.6.1,<1.7.0)
Requires-Dist: seaborn (>=0.12.2,<0.13.0)
Requires-Dist: smolagents (>=1.14.0,<2.0.0)
Requires-Dist: statsmodels (>=0.14.4,<0.15.0)
Requires-Dist: tenacity (>=9.0.0,<10.0.0)
Requires-Dist: tokenizers (>=0.21.1,<0.22.0) ; extra == "transformers" or extra == "all"
Requires-Dist: torch (>=2.3.0,<3.0.0)
Requires-Dist: transformers (>=4.50.0,<5.0.0) ; extra == "transformers" or extra == "all"
Requires-Dist: uvicorn[standard] (>=0.34.2,<0.35.0) ; extra == "chatui" or extra == "all"
Requires-Dist: websockets (>=12.0,<13.0) ; extra == "chatui" or extra == "all"
Requires-Dist: xgboost (>=2.1.3,<3.0.0)
Project-URL: Homepage, https://github.com/plexe-ai/plexe
Project-URL: Repository, https://github.com/plexe-ai/plexe
